opera_tosca_parser/__init__.py
opera_tosca_parser/cli.py
opera_tosca_parser/error.py
opera_tosca_parser/commands/__init__.py
opera_tosca_parser/commands/parse.py
opera_tosca_parser/parser/__init__.py
opera_tosca_parser/parser/tosca/__init__.py
opera_tosca_parser/parser/tosca/v_1_3/__init__.py
opera_tosca_parser/parser/tosca/v_1_3/base.py
opera_tosca_parser/parser/tosca/v_1_3/bool.py
opera_tosca_parser/parser/tosca/v_1_3/comparable.py
opera_tosca_parser/parser/tosca/v_1_3/constants.py
opera_tosca_parser/parser/tosca/v_1_3/csar.py
opera_tosca_parser/parser/tosca/v_1_3/entity.py
opera_tosca_parser/parser/tosca/v_1_3/integer.py
opera_tosca_parser/parser/tosca/v_1_3/list.py
opera_tosca_parser/parser/tosca/v_1_3/map.py
opera_tosca_parser/parser/tosca/v_1_3/path.py
opera_tosca_parser/parser/tosca/v_1_3/reference.py
opera_tosca_parser/parser/tosca/v_1_3/string.py
opera_tosca_parser/parser/tosca/v_1_3/timestamp.py
opera_tosca_parser/parser/tosca/v_1_3/type.py
opera_tosca_parser/parser/tosca/v_1_3/value.py
opera_tosca_parser/parser/tosca/v_1_3/version.py
opera_tosca_parser/parser/tosca/v_1_3/void.py
opera_tosca_parser/parser/tosca/v_1_3/definitions/__init__.py
opera_tosca_parser/parser/tosca/v_1_3/definitions/activity_definition.py
opera_tosca_parser/parser/tosca/v_1_3/definitions/artifact_definition.py
opera_tosca_parser/parser/tosca/v_1_3/definitions/artifact_type.py
opera_tosca_parser/parser/tosca/v_1_3/definitions/attribute_definition.py
opera_tosca_parser/parser/tosca/v_1_3/definitions/capability_assignment.py
opera_tosca_parser/parser/tosca/v_1_3/definitions/capability_definition.py
opera_tosca_parser/parser/tosca/v_1_3/definitions/capability_type.py
opera_tosca_parser/parser/tosca/v_1_3/definitions/collector_mixin.py
opera_tosca_parser/parser/tosca/v_1_3/definitions/condition_clause_definition.py
opera_tosca_parser/parser/tosca/v_1_3/definitions/constraint_clause.py
opera_tosca_parser/parser/tosca/v_1_3/definitions/credential.py
opera_tosca_parser-0.2.2.dist-info/LICENSE
opera_tosca_parser-0.2.2.dist-info/METADATA
opera_tosca_parser-0.2.2.dist-info/WHEEL
opera_tosca_parser-0.2.2.dist-info/entry_points.txt
opera_tosca_parser-0.2.2.dist-info/top_level.txt
opera_tosca_parser-0.2.2.dist-info/zip-safe
opera_tosca_parser-0.2.2.dist-info/RECORD
