Metadata-Version: 2.1
Name: opera-tosca-parser
Version: 0.2.2
Summary: xOpera TOSCA parser
Home-page: https://github.com/xlab-si/xopera-tosca-parser
Author: XLAB d.o.o.
Author-email: pypi@xlab.si
Maintainer: xOpera team
Maintainer-email: xopera@xlab.si
Project-URL: Documentation, https://xlab-si.github.io/xopera-docs/
Project-URL: Source Code, https://github.com/xlab-si/xopera-tosca-parser
Project-URL: Bug Tracker, https://github.com/xlab-si/xopera-tosca-parser/issues
Project-URL: Discussions, https://github.com/xlab-si/xopera-tosca-parser/discussions
Project-URL: Releases, https://github.com/xlab-si/xopera-tosca-parser/releases
Project-URL: Pre-releases, https://test.pypi.org/project/opera-tosca-parser/#history
Project-URL: Examples, https://github.com/xlab-si/xopera-examples
Project-URL: CI, https://github.com/xlab-si/xopera-tosca-parser/actions/
Keywords: orchestration
Classifier: Development Status :: 3 - Alpha
Classifier: Environment :: Console
Classifier: Intended Audience :: Developers
Classifier: Intended Audience :: System Administrators
Classifier: Intended Audience :: Science/Research
Classifier: Intended Audience :: Information Technology
Classifier: License :: OSI Approved :: Apache Software License
Classifier: Operating System :: POSIX
Classifier: Programming Language :: Python
Classifier: Programming Language :: Python :: 3
Classifier: Programming Language :: Python :: 3.8
Classifier: Programming Language :: Python :: 3.9
Classifier: Programming Language :: Python :: 3.10
Classifier: Programming Language :: Python :: 3.11
Classifier: Topic :: Software Development
Classifier: Topic :: Software Development :: Libraries
Classifier: Topic :: Software Development :: Libraries :: Python Modules
Classifier: Topic :: Utilities
Provides-Extra: test
License-File: LICENSE
